{
  "id": "bosnia-herzegovina",
  "nameZh": "波黑",
  "nameEn": "Bosnia-Herzegovina",
  "code": "ba",
  "group": "B",
  "confederation": "",
  "fifaRank": null,
  "flag": "https://flagcdn.com/w80/ba.png",
  "coach": {
    "nameEn": "Sergej Barbarez",
    "nameZh": "Sergej Barbarez",
    "nationality": "Bosnia-Herzegovina"
  },
  "founded": 1992,
  "venue": "",
  "squad": [
    {
      "name": "Martin Zlomislić",
      "nameZh": "Martin Zlomislić",
      "position": "Goalkeeper",
      "positionZh": "门将",
      "dateOfBirth": "1998-08-16",
      "nationality": "Bosnia-Herzegovina",
      "shirtNumber": null,
      "photo": "https://www.thesportsdb.com/images/media/player/cutout/nabcnf1779016971.png",
      "photoCutout": "https://www.thesportsdb.com/images/media/player/cutout/nabcnf1779016971.png",
      "photoThumb": "https://www.thesportsdb.com/images/media/player/thumb/uhsd4r1778541627.jpg"
    },
    {
      "name": "Nikola Vasilj",
      "nameZh": "Nikola Vasilj",
      "position": "Goalkeeper",
      "positionZh": "门将",
      "dateOfBirth": "1995-12-02",
      "nationality": "Bosnia-Herzegovina",
      "shirtNumber": null,
      "photo": "https://r2.thesportsdb.com/images/media/player/cutout/85qp2e1763567779.png",
      "photoCutout": "https://r2.thesportsdb.com/images/media/player/cutout/85qp2e1763567779.png",
      "photoThumb": "https://www.thesportsdb.com/images/media/player/thumb/cu1aj51778541706.jpg"
    },
    {
      "name": "Mladen Jurkas",
      "nameZh": "Mladen Jurkas",
      "position": "Goalkeeper",
      "positionZh": "门将",
      "dateOfBirth": "2007-10-07",
      "nationality": "Bosnia-Herzegovina",
      "shirtNumber": null
    },
    {
      "name": "Sead Kolašinac",
      "nameZh": "Sead Kolašinac",
      "position": "Defence",
      "positionZh": "后卫",
      "dateOfBirth": "1993-06-20",
      "nationality": "Bosnia-Herzegovina",
      "shirtNumber": null,
      "photo": "https://r2.thesportsdb.com/images/media/player/cutout/ae2jmk1695157289.png",
      "photoCutout": "https://r2.thesportsdb.com/images/media/player/cutout/ae2jmk1695157289.png",
      "photoThumb": "https://r2.thesportsdb.com/images/media/player/thumb/kzf4g21510852753.jpg"
    },
    {
      "name": "Dennis Hadžikadunić",
      "nameZh": "Dennis Hadžikadunić",
      "position": "Defence",
      "positionZh": "后卫",
      "dateOfBirth": "1998-07-09",
      "nationality": "Bosnia-Herzegovina",
      "shirtNumber": null,
      "photo": "https://commons.wikimedia.org/wiki/Special:FilePath/Dennis_Hadžikadunić_2021.jpg?width=500",
      "photoThumb": "https://commons.wikimedia.org/wiki/Special:FilePath/Dennis_Hadžikadunić_2021.jpg?width=500"
    },
    {
      "name": "Nihad Mujakić",
      "nameZh": "Nihad Mujakić",
      "position": "Defence",
      "positionZh": "后卫",
      "dateOfBirth": "1998-04-15",
      "nationality": "Bosnia-Herzegovina",
      "shirtNumber": null,
      "photo": "https://www.thesportsdb.com/images/media/player/cutout/b961ge1779017042.png",
      "photoCutout": "https://www.thesportsdb.com/images/media/player/cutout/b961ge1779017042.png",
      "photoThumb": "https://www.thesportsdb.com/images/media/player/thumb/khqfz21778541096.jpg"
    },
    {
      "name": "Nikola Katić",
      "nameZh": "Nikola Katić",
      "position": "Defence",
      "positionZh": "后卫",
      "dateOfBirth": "1996-10-10",
      "nationality": "Bosnia-Herzegovina",
      "shirtNumber": null,
      "photo": "https://r2.thesportsdb.com/images/media/player/cutout/tnvi3o1773611092.png",
      "photoCutout": "https://r2.thesportsdb.com/images/media/player/cutout/tnvi3o1773611092.png",
      "photoThumb": "https://www.thesportsdb.com/images/media/player/thumb/1b7s0n1778542342.jpg"
    },
    {
      "name": "Stjepan Radeljić",
      "nameZh": "Stjepan Radeljić",
      "position": "Defence",
      "positionZh": "后卫",
      "dateOfBirth": "1997-09-05",
      "nationality": "Bosnia-Herzegovina",
      "shirtNumber": null,
      "photo": "https://www.thesportsdb.com/images/media/player/cutout/umezbz1779017106.png",
      "photoCutout": "https://www.thesportsdb.com/images/media/player/cutout/umezbz1779017106.png",
      "photoThumb": "https://www.thesportsdb.com/images/media/player/thumb/rydyw41778541203.jpg"
    },
    {
      "name": "Amar Dedić",
      "nameZh": "Amar Dedić",
      "position": "Defence",
      "positionZh": "后卫",
      "dateOfBirth": "2002-08-18",
      "nationality": "Austria",
      "shirtNumber": null,
      "photo": "https://r2.thesportsdb.com/images/media/player/cutout/3qhv951758216357.png",
      "photoCutout": "https://r2.thesportsdb.com/images/media/player/cutout/3qhv951758216357.png",
      "photoThumb": "https://www.thesportsdb.com/images/media/player/thumb/y4f55i1778543039.jpg"
    },
    {
      "name": "Tarik Muharemović",
      "nameZh": "Tarik Muharemović",
      "position": "Defence",
      "positionZh": "后卫",
      "dateOfBirth": "2003-02-28",
      "nationality": "Bosnia-Herzegovina",
      "shirtNumber": null,
      "photo": "https://r2.thesportsdb.com/images/media/player/cutout/zrpkc31764106120.png",
      "photoCutout": "https://r2.thesportsdb.com/images/media/player/cutout/zrpkc31764106120.png",
      "photoThumb": "https://r2.thesportsdb.com/images/media/player/thumb/2s76nh1764103543.jpg"
    },
    {
      "name": "Arjan Malic",
      "nameZh": "Arjan Malic",
      "position": "Defence",
      "positionZh": "后卫",
      "dateOfBirth": "2005-08-28",
      "nationality": "Bosnia-Herzegovina",
      "shirtNumber": null
    },
    {
      "name": "Dženis Burnić",
      "nameZh": "Dženis Burnić",
      "position": "Midfield",
      "positionZh": "中场",
      "dateOfBirth": "1998-05-22",
      "nationality": "Bosnia-Herzegovina",
      "shirtNumber": null,
      "photo": "https://r2.thesportsdb.com/images/media/player/cutout/mohhc51773244613.png",
      "photoCutout": "https://r2.thesportsdb.com/images/media/player/cutout/mohhc51773244613.png",
      "photoThumb": "https://www.thesportsdb.com/images/media/player/thumb/ertan61778542638.jpg"
    },
    {
      "name": "Ivan Šunjić",
      "nameZh": "Ivan Šunjić",
      "position": "Midfield",
      "positionZh": "中场",
      "dateOfBirth": "1996-10-09",
      "nationality": "Bosnia-Herzegovina",
      "shirtNumber": null
    },
    {
      "name": "Amir Hadžiahmetović",
      "nameZh": "Amir Hadžiahmetović",
      "position": "Midfield",
      "positionZh": "中场",
      "dateOfBirth": "1997-03-08",
      "nationality": "Bosnia-Herzegovina",
      "shirtNumber": null,
      "photo": "https://r2.thesportsdb.com/images/media/player/cutout/d701ms1761922073.png",
      "photoCutout": "https://r2.thesportsdb.com/images/media/player/cutout/d701ms1761922073.png",
      "photoThumb": "https://r2.thesportsdb.com/images/media/player/thumb/q1cm1n1756817163.jpg"
    },
    {
      "name": "Armin Gigovic",
      "nameZh": "Armin Gigovic",
      "position": "Midfield",
      "positionZh": "中场",
      "dateOfBirth": "2002-04-06",
      "nationality": "Bosnia-Herzegovina",
      "shirtNumber": null,
      "photo": "https://r2.thesportsdb.com/images/media/player/cutout/esyc771742067604.png",
      "photoCutout": "https://r2.thesportsdb.com/images/media/player/cutout/esyc771742067604.png",
      "photoThumb": "https://www.thesportsdb.com/images/media/player/thumb/1azb771778543473.jpg"
    },
    {
      "name": "Ivan Bašić",
      "nameZh": "Ivan Bašić",
      "position": "Midfield",
      "positionZh": "中场",
      "dateOfBirth": "2002-04-30",
      "nationality": "Bosnia-Herzegovina",
      "shirtNumber": null,
      "photo": "https://r2.thesportsdb.com/images/media/player/cutout/247gi31726000720.png",
      "photoCutout": "https://r2.thesportsdb.com/images/media/player/cutout/247gi31726000720.png",
      "photoThumb": "https://www.thesportsdb.com/images/media/player/thumb/6bxzh41778544071.jpg"
    },
    {
      "name": "Benjamin Tahirovic",
      "nameZh": "Benjamin Tahirovic",
      "position": "Midfield",
      "positionZh": "中场",
      "dateOfBirth": "2003-03-03",
      "nationality": "Bosnia-Herzegovina",
      "shirtNumber": null,
      "photo": "https://r2.thesportsdb.com/images/media/player/cutout/wrr6m21765376681.png",
      "photoCutout": "https://r2.thesportsdb.com/images/media/player/cutout/wrr6m21765376681.png",
      "photoThumb": "https://r2.thesportsdb.com/images/media/player/thumb/pny4wf1679566380.jpg"
    },
    {
      "name": "Ermin Mahmic",
      "nameZh": "Ermin Mahmic",
      "position": "Midfield",
      "positionZh": "中场",
      "dateOfBirth": "2005-03-14",
      "nationality": "Bosnia and Herzegovina",
      "shirtNumber": null
    },
    {
      "name": "Amar Memić",
      "nameZh": "Amar Memić",
      "position": "Midfield",
      "positionZh": "中场",
      "dateOfBirth": "2001-01-20",
      "nationality": "Bosnia-Herzegovina",
      "shirtNumber": null,
      "photo": "https://www.thesportsdb.com/images/media/player/cutout/bcyk9s1779017172.png",
      "photoCutout": "https://www.thesportsdb.com/images/media/player/cutout/bcyk9s1779017172.png",
      "photoThumb": "https://www.thesportsdb.com/images/media/player/thumb/3emqu01778540725.jpg"
    },
    {
      "name": "Edin Džeko",
      "nameZh": "Edin Džeko",
      "position": "Offence",
      "positionZh": "前锋",
      "dateOfBirth": "1986-03-17",
      "nationality": "Bosnia-Herzegovina",
      "shirtNumber": null,
      "photo": "https://r2.thesportsdb.com/images/media/player/cutout/0jo14d1773611434.png",
      "photoCutout": "https://r2.thesportsdb.com/images/media/player/cutout/0jo14d1773611434.png",
      "photoThumb": "https://r2.thesportsdb.com/images/media/player/thumb/sml4xg1710662840.jpg"
    },
    {
      "name": "Jovo Lukić",
      "nameZh": "Jovo Lukić",
      "position": "Offence",
      "positionZh": "前锋",
      "dateOfBirth": "1998-11-28",
      "nationality": "Bosnia-Herzegovina",
      "shirtNumber": null
    },
    {
      "name": "Ermedin Demirovic",
      "nameZh": "Ermedin Demirovic",
      "position": "Offence",
      "positionZh": "前锋",
      "dateOfBirth": "1998-03-25",
      "nationality": "Bosnia-Herzegovina",
      "shirtNumber": null,
      "photo": "https://r2.thesportsdb.com/images/media/player/cutout/hvuj8v1763586169.png",
      "photoCutout": "https://r2.thesportsdb.com/images/media/player/cutout/hvuj8v1763586169.png",
      "photoThumb": "https://www.thesportsdb.com/images/media/player/thumb/ahykd01778543129.jpg"
    },
    {
      "name": "Haris Tabaković",
      "nameZh": "Haris Tabaković",
      "position": "Offence",
      "positionZh": "前锋",
      "dateOfBirth": "1994-06-20",
      "nationality": "Bosnia-Herzegovina",
      "shirtNumber": null,
      "photo": "https://r2.thesportsdb.com/images/media/player/cutout/rjvats1756313128.png",
      "photoCutout": "https://r2.thesportsdb.com/images/media/player/cutout/rjvats1756313128.png",
      "photoThumb": "https://www.thesportsdb.com/images/media/player/thumb/2shpb51778541916.jpg"
    },
    {
      "name": "Samed Bazdar",
      "nameZh": "Samed Bazdar",
      "position": "Offence",
      "positionZh": "前锋",
      "dateOfBirth": "2004-01-31",
      "nationality": "Bosnia-Herzegovina",
      "shirtNumber": null,
      "photo": "https://www.thesportsdb.com/images/media/player/cutout/o3tqwz1779017584.png",
      "photoCutout": "https://www.thesportsdb.com/images/media/player/cutout/o3tqwz1779017584.png",
      "photoThumb": "https://www.thesportsdb.com/images/media/player/thumb/mh04pv1778539701.jpg"
    },
    {
      "name": "Esmir Bajraktarevic",
      "nameZh": "Esmir Bajraktarevic",
      "position": "Offence",
      "positionZh": "前锋",
      "dateOfBirth": "2005-03-10",
      "nationality": "Bosnia-Herzegovina",
      "shirtNumber": null,
      "photo": "https://r2.thesportsdb.com/images/media/player/cutout/896xbs1764594499.png",
      "photoCutout": "https://r2.thesportsdb.com/images/media/player/cutout/896xbs1764594499.png",
      "photoThumb": "https://www.thesportsdb.com/images/media/player/thumb/tt22l31778539825.jpg"
    },
    {
      "name": "Kerim Alajbegović",
      "nameZh": "Kerim Alajbegović",
      "position": "Offence",
      "positionZh": "前锋",
      "dateOfBirth": "2007-09-21",
      "nationality": "Bosnia-Herzegovina",
      "shirtNumber": null,
      "photo": "https://r2.thesportsdb.com/images/media/player/cutout/sfkv2p1769721901.png",
      "photoCutout": "https://r2.thesportsdb.com/images/media/player/cutout/sfkv2p1769721901.png",
      "photoThumb": "https://www.thesportsdb.com/images/media/player/thumb/2dtxv61778542471.jpg"
    }
  ],
  "squadStatus": "incomplete",
  "squadLastUpdated": "2026-06-28",
  "squadSourceUrl": "https://www.fifa.com/en/tournaments/mens/worldcup/canadamexicousa2026/articles/all-world-cup-squad-announcements",
  "recentMatches": [
    {
      "date": "2026-06-24",
      "competition": "FIFA World Cup",
      "homeTeam": "Bosnia-Herzegovina",
      "awayTeam": "Qatar",
      "scoreHome": 3,
      "scoreAway": 1,
      "result": "W"
    },
    {
      "date": "2026-06-18",
      "competition": "FIFA World Cup",
      "homeTeam": "Switzerland",
      "awayTeam": "Bosnia-Herzegovina",
      "scoreHome": 4,
      "scoreAway": 1,
      "result": "L"
    },
    {
      "date": "2026-06-12",
      "competition": "FIFA World Cup",
      "homeTeam": "Canada",
      "awayTeam": "Bosnia-Herzegovina",
      "scoreHome": 1,
      "scoreAway": 1,
      "result": "D"
    }
  ]
}